{
    "appid": "1338040",
    "common": {
        "name": "Automobilista 2 - Dedicated Server",
        "type": "Tool",
        "parent": "1066890",
        "releasestate": "released",
        "logo": "da409d82270283b39d3fe750acfef7d639745cd8",
        "logo_small": "da409d82270283b39d3fe750acfef7d639745cd8_thumb",
        "icon": "c3099dee505501dc6ca8800ff9042495729d2903",
        "clienticon": "619c117330af778dc9669b75e78c026048a462d5",
        "clienttga": "299eab4abeee2aae735c98cda8bd71aadfe4fa04",
        "oslist": "windows",
        "osarch": "",
        "osextended": "",
        "associations": {},
        "gameid": "1338040"
    },
    "config": {
        "installdir": "Automobilista 2 - Dedicated Server",
        "launch": {
            "0": {
                "executable": "DedicatedServerCmd.exe",
                "type": "server",
                "config": {
                    "oslist": "windows"
                }
            }
        }
    },
    "depots": {
        "1338041": {
            "config": {
                "oslist": "windows",
                "language": ""
            },
            "manifests": {
                "public": {
                    "gid": "7051879729974958815",
                    "size": "15992765",
                    "download": "5185344"
                }
            },
            "encryptedmanifests": {
                "stagingtest": {
                    "gid": "50CE4418A349ABFE6E302AB7B2BE56DC",
                    "size": "48D3D46FF727DB2EFA9F4D0BF96D2533",
                    "download": "B90AA249423873665C2FDA989F55D74C"
                }
            }
        },
        "branches": {
            "public": {
                "buildid": "13069777",
                "timeupdated": "1704037024"
            },
            "stagingtest": {
                "buildid": "13069777",
                "pwdrequired": "1",
                "timeupdated": "1704036976"
            }
        }
    },
    "_missing_token": false,
    "_change_number": 21720016,
    "_sha": "8ad8df282bcc48d15d686c7a8df1bbde8c4bae96",
    "_size": 1432
}