{
    "appid": "258550",
    "common": {
        "name": "Rust Dedicated Server",
        "type": "Game",
        "releasestate": "released",
        "oslist": "windows,linux",
        "osarch": "",
        "osextended": "",
        "associations": {},
        "gameid": "258550",
        "store_tags": {}
    },
    "extended": {
        "gamedir": ""
    },
    "config": {
        "contenttype": "3",
        "installdir": "rust_dedicated"
    },
    "depots": {
        "overridescddb": "1",
        "markdlcdepots": "1",
        "258551": {
            "systemdefined": "1",
            "config": {
                "oslist": "windows"
            },
            "manifests": {
                "public": {
                    "gid": "4032127962874706061",
                    "size": "629461644",
                    "download": "408945552"
                },
                "aux01": {
                    "gid": "54235556778710650",
                    "size": "620673941",
                    "download": "406281904"
                },
                "aux02": {
                    "gid": "398274161329262343",
                    "size": "625423347",
                    "download": "407158608"
                },
                "aux03": {
                    "gid": "3977822378240546837",
                    "size": "629788725",
                    "download": "409038800"
                },
                "debug": {
                    "gid": "2591346971987511447",
                    "size": "631208934",
                    "download": "393851888"
                },
                "last-month": {
                    "gid": "5434512232985231584",
                    "size": "594678309",
                    "download": "384215456"
                },
                "release": {
                    "gid": "4181030070532810022",
                    "size": "629478540",
                    "download": "408945616"
                },
                "staging": {
                    "gid": "2002023501411570487",
                    "size": "625376279",
                    "download": "407142384"
                }
            }
        },
        "258552": {
            "config": {
                "oslist": "linux"
            },
            "manifests": {
                "public": {
                    "gid": "4447642848007252922",
                    "size": "647588978",
                    "download": "382484352"
                },
                "aux01": {
                    "gid": "949630714142880006",
                    "size": "633254403",
                    "download": "379782080"
                },
                "aux02": {
                    "gid": "8399354074442673690",
                    "size": "643533937",
                    "download": "380620112"
                },
                "aux03": {
                    "gid": "2413408819543760872",
                    "size": "647898723",
                    "download": "382488560"
                },
                "debug": {
                    "gid": "8305401038939912362",
                    "size": "139415558",
                    "download": "34397936"
                },
                "last-month": {
                    "gid": "5464837686115944412",
                    "size": "631381847",
                    "download": "376852432"
                },
                "release": {
                    "gid": "9145782128713277103",
                    "size": "647934650",
                    "download": "382580128"
                },
                "staging": {
                    "gid": "3379171929154092317",
                    "size": "643492269",
                    "download": "380592112"
                }
            }
        },
        "258554": {
            "manifests": {
                "public": {
                    "gid": "6160524892256366788",
                    "size": "8239345536",
                    "download": "2017332544"
                },
                "aux01": {
                    "gid": "8920793311077920065",
                    "size": "8553881438",
                    "download": "2212480736"
                },
                "aux02": {
                    "gid": "3218138404956919499",
                    "size": "8267424902",
                    "download": "2029562224"
                },
                "aux03": {
                    "gid": "5582418131149365382",
                    "size": "8240644128",
                    "download": "2017673664"
                },
                "debug": {
                    "gid": "9050441631359858310",
                    "size": "8000428058",
                    "download": "1942290304"
                },
                "last-month": {
                    "gid": "1453623735786069882",
                    "size": "8004379972",
                    "download": "1943609440"
                },
                "release": {
                    "gid": "1286899529040638416",
                    "size": "8239348112",
                    "download": "2017336080"
                },
                "staging": {
                    "gid": "7475396383504650818",
                    "size": "8240231120",
                    "download": "2017616224"
                }
            }
        },
        "branches": {
            "public": {
                "buildid": "17364630",
                "timeupdated": "1739528050"
            },
            "aux01": {
                "buildid": "16999813",
                "description": "Pre-Staging",
                "timeupdated": "1736859300"
            },
            "aux02": {
                "buildid": "17412305",
                "description": "Up and coming",
                "timeupdated": "1739907238"
            },
            "aux03": {
                "buildid": "17393050",
                "description": "aux03",
                "timeupdated": "1739796117"
            },
            "debug": {
                "buildid": "17041002",
                "description": "2021 testing",
                "timeupdated": "1737126347"
            },
            "last-month": {
                "buildid": "17118157",
                "description": "last-month",
                "timeupdated": "1738866558"
            },
            "release": {
                "buildid": "17410159",
                "timeupdated": "1739896617"
            },
            "staging": {
                "buildid": "17412422",
                "timeupdated": "1739907936"
            }
        },
        "privatebranches": "1"
    },
    "_missing_token": false,
    "_change_number": 27541240,
    "_sha": "cebfaa7ebde92a1d336080db9758814b9fff775e",
    "_size": 4251
}