{
    "appid": "293030",
    "common": {
        "name": "Contagion Dedicated Server",
        "type": "Tool",
        "releasestate": "released",
        "parent": "238430",
        "oslist": "windows",
        "logo": "8ec7c8b7cced70ff7fe3de10cad80daa83a92957",
        "logo_small": "8ec7c8b7cced70ff7fe3de10cad80daa83a92957_thumb",
        "icon": "d483ac635feea91250e13639cfff2e74a49d4261",
        "clienticon": "00326093e2661b0707ffa191a47db7db261da439",
        "clienttga": "4d32ef2ac080fbfbd1de08529298ffd26d3e3130",
        "osarch": "",
        "osextended": "",
        "associations": {},
        "gameid": "293030"
    },
    "config": {
        "contenttype": "3",
        "installdir": "Contagion Dedicated Server",
        "launch": {
            "0": {
                "executable": "contagionds.exe",
                "arguments": "-secure -steam",
                "type": "default",
                "config": {
                    "oslist": "windows"
                }
            },
            "1": {
                "executable": "contagion_dedicated",
                "arguments": "-secure -steam -game contagion",
                "type": "default",
                "config": {
                    "oslist": "linux"
                }
            }
        }
    },
    "depots": {
        "overridescddb": "1",
        "1004": {
            "config": {
                "oslist": "windows"
            },
            "manifests": {
                "public": "5329354416203291021"
            },
            "maxsize": "42086632",
            "depotfromapp": "1007"
        },
        "1005": {
            "config": {
                "oslist": "macos"
            },
            "manifests": {
                "public": "2135359612286175146"
            },
            "depotfromapp": "1007"
        },
        "1006": {
            "config": {
                "oslist": "linux"
            },
            "manifests": {
                "public": "4444585935428744334"
            },
            "maxsize": "66706004",
            "depotfromapp": "1007"
        },
        "228985": {
            "config": {
                "oslist": "windows"
            },
            "maxsize": "13699237",
            "depotfromapp": "228980",
            "sharedinstall": "1"
        },
        "293031": {
            "systemdefined": "1",
            "config": {
                "language": ""
            },
            "manifests": {
                "public": "1188427908609237689"
            },
            "maxsize": "12964184807",
            "encryptedmanifests": {
                "developer": {
                    "encrypted_gid_2": "4BC26F1AC458BED3DAA24537C7360D6A",
                    "encrypted_size_2": "FB4E809D7FFF95280A94715A3EC7F3DC",
                    "download": "032621904BEB9D421A43C045BEA00F1F"
                },
                "quality_assurance": {
                    "encrypted_gid_2": "E3044233E7E76E6302CD72D488A7C3E7",
                    "encrypted_size_2": "C56A35E84083E35B1266418233907022",
                    "download": "10A0E87F484FEFC0D572BEA7A85D89D6"
                }
            }
        },
        "293032": {
            "config": {
                "oslist": "windows",
                "language": ""
            },
            "manifests": {
                "public": "601991912790968817"
            },
            "maxsize": "87121585",
            "encryptedmanifests": {
                "developer": {
                    "encrypted_gid_2": "70CB5FDEDDB05B2BC90F6B58E25EC0D5",
                    "encrypted_size_2": "7DAA64B20A19102DC4E62CB9774036AA",
                    "download": "1495B7F2B40BAF9C64C60A7F665AEAEB"
                },
                "quality_assurance": {
                    "encrypted_gid_2": "1252EE758E4518FD2ABA033480E01D73",
                    "encrypted_size_2": "3B4DFC2A4E67743830DD5964AB2C1C04",
                    "download": "4FFDB7508C722263E0D25676535C15DC"
                }
            }
        },
        "293033": {
            "config": {
                "oslist": "linux",
                "language": ""
            },
            "manifests": {
                "public": "1748948970844579195"
            },
            "maxsize": "603069",
            "encryptedmanifests": {
                "developer": {
                    "encrypted_gid_2": "3EFFEC35129247C8DE7C79F1FFEA1F13",
                    "encrypted_size_2": "07D50610C99465752D55263349EEA370",
                    "download": "14F4C5E1ED8C4EC955C5F4416131D3D8"
                },
                "quality_assurance": {
                    "encrypted_gid_2": "4D68D3345491D6888336F364774BB58D",
                    "encrypted_size_2": "F4F3BA70ECCD8994BE17973F789D6AF0",
                    "download": "0B5BDA2E83FFA317ADD1918D151F6CD5"
                }
            }
        },
        "branches": {
            "public": {
                "buildid": "10884395",
                "timeupdated": "1680107711"
            },
            "developer": {
                "buildid": "7716160",
                "pwdrequired": "1",
                "timeupdated": "1636995203"
            },
            "quality_assurance": {
                "buildid": "10926814",
                "pwdrequired": "1",
                "timeupdated": "1680607259"
            }
        }
    },
    "_missing_token": false,
    "_change_number": 18322235,
    "_sha": "98660d1050110deaf95dbcee38d89d7f239d32bd",
    "_size": 3808
}