{
    "appid": "630230",
    "common": {
        "name": "DNL Dedicated Server",
        "type": "Tool",
        "parent": "529180",
        "releasestate": "released",
        "oslist": "windows",
        "osarch": "",
        "logo": "95526b2b11aa408242f32dfdb617b67eed829b60",
        "logo_small": "95526b2b11aa408242f32dfdb617b67eed829b60_thumb",
        "icon": "0e134101796768a5c1f2f2d0798ab79c50b54aa3",
        "clienttga": "9e26ed8977e3d5c78328e1091c45c9527a6fcbc4",
        "clienticon": "ae63227e1ec5f71672e7300bbe4eebe0d8b5c9c3",
        "app_retired_publisher_request": "1",
        "metacritic_name": "DNL Dedicated Server Tool",
        "small_capsule": {
            "english": "capsule_231x87.jpg"
        },
        "header_image": {
            "english": "header.jpg"
        },
        "library_assets": {
            "library_capsule": "en",
            "library_hero": "en",
            "library_logo": "en",
            "logo_position": {
                "pinned_position": "BottomLeft",
                "width_pct": "52.100350058343054",
                "height_pct": "59.878888625029674"
            }
        },
        "store_asset_mtime": "1572303203",
        "associations": {
            "0": {
                "type": "developer",
                "name": "Snail Games USA"
            },
            "1": {
                "type": "publisher",
                "name": "Snail Games USA"
            }
        },
        "primary_genre": "1",
        "genres": {
            "0": "1",
            "1": "25",
            "2": "3",
            "3": "28"
        },
        "category": {
            "category_2": "1",
            "category_1": "1",
            "category_36": "1",
            "category_49": "1"
        },
        "supported_languages": {
            "english": {
                "supported": "true"
            }
        },
        "original_release_date": "1500620400",
        "steam_release_date": "1501777848",
        "community_hub_visible": "1",
        "gameid": "630230"
    },
    "extended": {
        "developer": "Snail Games USA",
        "publisher": "Snail Games USA",
        "homepage": "http://www.playdnl.com/"
    },
    "config": {
        "installdir": "DNL Dedicated Server",
        "launch": {
            "0": {
                "executable": "DNL\\Binaries\\Win64\\DNLServer.exe",
                "workingdir": "DNL\\Binaries\\Win64\\",
                "type": "none",
                "config": {
                    "oslist": "windows"
                }
            }
        }
    },
    "depots": {
        "1004": {
            "config": {
                "oslist": "windows"
            },
            "manifests": {
                "public": "4660701598619066954"
            },
            "maxsize": "43850712",
            "depotfromapp": "1007"
        },
        "1005": {
            "config": {
                "oslist": "macos"
            },
            "manifests": {
                "public": "2135359612286175146"
            },
            "depotfromapp": "1007"
        },
        "1006": {
            "config": {
                "oslist": "linux"
            },
            "manifests": {
                "public": "6912453647411644579"
            },
            "maxsize": "72573740",
            "depotfromapp": "1007"
        },
        "228981": {
            "config": {
                "oslist": "windows"
            },
            "maxsize": "5884085",
            "depotfromapp": "228980",
            "sharedinstall": "1"
        },
        "228982": {
            "config": {
                "oslist": "windows"
            },
            "maxsize": "9688647",
            "depotfromapp": "228980",
            "sharedinstall": "1"
        },
        "228983": {
            "config": {
                "oslist": "windows"
            },
            "maxsize": "19265607",
            "depotfromapp": "228980",
            "sharedinstall": "1"
        },
        "228984": {
            "config": {
                "oslist": "windows"
            },
            "maxsize": "13742505",
            "depotfromapp": "228980",
            "sharedinstall": "1"
        },
        "228985": {
            "config": {
                "oslist": "windows"
            },
            "maxsize": "13699237",
            "depotfromapp": "228980",
            "sharedinstall": "1"
        },
        "228986": {
            "config": {
                "oslist": "windows"
            },
            "maxsize": "29759921",
            "depotfromapp": "228980",
            "sharedinstall": "1"
        },
        "228990": {
            "config": {
                "oslist": "windows"
            },
            "maxsize": "102931551",
            "depotfromapp": "228980",
            "sharedinstall": "1"
        },
        "baselanguages": "english",
        "630231": {
            "manifests": {
                "public": {
                    "gid": "1305063167786399795",
                    "size": "3703510879",
                    "download": "1386726368"
                }
            },
            "encryptedmanifests": {
                "closedtest": {
                    "gid": "71FE65B26F946189AE854DC67FEED7DC",
                    "size": "BFB33C61EBD033182431F60F5C28BB58",
                    "download": "DD8E7AB77FAB5031B0CB22E63793EF51"
                },
                "closedtestb": {
                    "gid": "3EAB8B937CE73D54B8B6DB4CE79DBDE0",
                    "size": "6A447CFD84F6E2C954939C3AAB5E3422",
                    "download": "872D2353CE6DE8A33209DD7CAFAB0EE9"
                },
                "development": {
                    "gid": "B5DFCD17599091D0AA1CAC000471D6AD",
                    "size": "C70DA3D3D72EC1BD41DFC3F5B69629B5",
                    "download": "226A4E2F607621265D361D5BC9242E5D"
                },
                "marketing": {
                    "gid": "3DB5140E7D3D6605D6CB5E2AF345F843",
                    "size": "8707034CDBA29D56D320CACD7BBCDE61",
                    "download": "4B3F90E783CF539DC064C1560DE977D0"
                },
                "pre-release": {
                    "gid": "03A616E22B7C45EB5EB03AC6E095606D",
                    "size": "FFDA7CC3B67F1A534246CB9E110B0F36",
                    "download": "1F621202B3EFFDC7B3E2F9744AC11443"
                },
                "staging": {
                    "gid": "F10253D8F07AEF4ED51708F3602A5AB6",
                    "size": "1A1AA7AD8C4769627D242CA70AD53921",
                    "download": "E796AFA2A231005D4E0E01D03AD952A8"
                }
            }
        },
        "branches": {
            "public": {
                "buildid": "4376452",
                "timeupdated": "1573718171"
            },
            "closedtest": {
                "buildid": "3158816",
                "pwdrequired": "1",
                "timeupdated": "1538010947"
            },
            "closedtestb": {
                "buildid": "4376452",
                "pwdrequired": "1",
                "timeupdated": "1573542373"
            },
            "development": {
                "buildid": "4314306",
                "pwdrequired": "1",
                "timeupdated": "1571811687"
            },
            "marketing": {
                "buildid": "2449676",
                "pwdrequired": "1",
                "timeupdated": "1516344501"
            },
            "pre-release": {
                "buildid": "2997520",
                "pwdrequired": "1",
                "timeupdated": "1533605320"
            },
            "staging": {
                "buildid": "3106354",
                "pwdrequired": "1",
                "timeupdated": "1536648671"
            }
        }
    },
    "_missing_token": false,
    "_change_number": 18903802,
    "_sha": "173804db17e2ebffe13028faf4bef41b9d1fc65d",
    "_size": 5430
}