{
    "appid": "774961",
    "common": {
        "name": "Squad - Public Test Dedicated Server",
        "type": "Tool",
        "parent": "774941",
        "releasestate": "released",
        "oslist": "windows,linux",
        "osarch": "",
        "clienttga": "d26cb41f9f79cce4cc6bcbd40bc3e63e947d98a4",
        "clienticon": "5cb6171b179fd2dc6a4a2dc49ef1760d0d839282",
        "icon": "e02936d5dda8f41ce8c480d4b3e8af1e8d3db18c",
        "associations": {},
        "gameid": "774961"
    },
    "extended": {
        "gamedir": ""
    },
    "config": {
        "installdir": "Squad - Public Test Dedicated Server",
        "launch": {
            "0": {
                "executable": "SquadServer.exe",
                "type": "default",
                "config": {
                    "oslist": "windows",
                    "osarch": "64"
                }
            },
            "1": {
                "executable": "SquadServer.sh",
                "type": "server",
                "config": {
                    "oslist": "linux",
                    "osarch": "64"
                }
            }
        }
    },
    "depots": {
        "baselanguages": "english",
        "hasdepotsindlc": "0",
        "1004": {
            "config": {
                "oslist": "windows"
            },
            "manifests": {
                "public": {
                    "gid": "4660701598619066954",
                    "size": "43850712",
                    "download": "13716400"
                }
            },
            "depotfromapp": "1007"
        },
        "1005": {
            "config": {
                "oslist": "macos"
            },
            "manifests": {
                "public": {
                    "gid": "2135359612286175146",
                    "size": "0",
                    "download": "0"
                }
            },
            "depotfromapp": "1007"
        },
        "1006": {
            "config": {
                "oslist": "linux"
            },
            "manifests": {
                "public": {
                    "gid": "6912453647411644579",
                    "size": "72573740",
                    "download": "20021152"
                }
            },
            "depotfromapp": "1007"
        },
        "228985": {
            "config": {
                "oslist": "windows"
            },
            "depotfromapp": "228980",
            "sharedinstall": "1"
        },
        "228986": {
            "config": {
                "oslist": "windows"
            },
            "depotfromapp": "228980",
            "sharedinstall": "1"
        },
        "228990": {
            "config": {
                "oslist": "windows"
            },
            "depotfromapp": "228980",
            "sharedinstall": "1"
        },
        "774962": {
            "config": {
                "oslist": "windows",
                "osarch": "64",
                "language": ""
            },
            "manifests": {
                "public": {
                    "gid": "9218183786785996521",
                    "size": "10802266611",
                    "download": "3355227472"
                }
            },
            "encryptedmanifests": {
                "uat_community_hosting": {
                    "gid": "88B82DB2401CF8D1190AD1862F1A6365",
                    "size": "664806763EEF080A1C9F0EC0FC312B99",
                    "download": "27D730D09265BCEB4487552F2AB37C4B"
                },
                "uat_content": {
                    "gid": "E96AAA214F94229885209AB4815B3805",
                    "size": "941823F5383CDC8E4CAF897F2B8851BE",
                    "download": "1A49E511EAB5851D64268F737F609A02"
                },
                "uat_content_pt": {
                    "gid": "66BDD866C0C5FE8F28C7F69AE9B0F4F3",
                    "size": "1B835F84B645A62719E5428CC4BEA6C5",
                    "download": "4F7123FCDAC8D22ED0524B5765216DBA"
                },
                "uat_cpt": {
                    "gid": "542473D2985157A07809B91B36DC5E74",
                    "size": "5C8FDC47C0404D946C58833A6582C9C1",
                    "download": "7EF7799FAC306292DB728744C19D190A"
                },
                "uat_crashtest": {
                    "gid": "3F2C70EC1CBCC6B4A3CA168628D3C2EC",
                    "size": "D4DA277E90F9E98235E6C7C088B200FF",
                    "download": "BFDEEBB2F2FE640D4E1454A160987C76"
                },
                "uat_features": {
                    "gid": "1EB179EF76370EC6CCCE177D892EAE1E",
                    "size": "3B85B0036F1CC40D7D08FF9BAD832017",
                    "download": "52BF09172CA1EF4F4F0B5F0E30D4993D"
                },
                "uat_features_rc": {
                    "gid": "9822BE2FC1605119035D5AC61DADA60F",
                    "size": "158094DBBCED2555D51E39EA8ABBA69D",
                    "download": "4F4E005D921BDC608824009CE0121C42"
                },
                "uat_featuretest1": {
                    "gid": "0E3E47C32A6CB3279B9706E060E457F3",
                    "size": "2CC44B2E2F51B5F88431910131BAA375",
                    "download": "8E0DCD358C03E37EB7B6ADFACA049479"
                },
                "uat_featuretest10": {
                    "gid": "C09135D7C76913F42E441A302FED019D",
                    "size": "A6ADCE0C9B6E235FCD92FAF2270EF914",
                    "download": "C8EF152957B8E0CDF261B44D61C1ED25"
                },
                "uat_featuretest11": {
                    "gid": "AE40C52CCA5EE6FD461C46D05B7D09F4",
                    "size": "E7323B7783006070239B4B6360108DDE",
                    "download": "9EC529DBE74AE72D528FE50EC5DB4892"
                },
                "uat_featuretest2": {
                    "gid": "6D39A833AEEF526679CE4728C0B085A1",
                    "size": "3E6583689F9B5789F4B3D4085BD81DC3",
                    "download": "C866C4BB963F9F34788197E1BF10BDDA"
                },
                "uat_featuretest3": {
                    "gid": "32EFF16AD47B99262FD441CE00224100",
                    "size": "145C1504BB34EAF51B781C1F6353381E",
                    "download": "71B28D51EC920371E57C1FCCDE83F97D"
                },
                "uat_featuretest4": {
                    "gid": "7B95B2097590F4C48C88BF77C37489F7",
                    "size": "81BE72C7B61458F0D58C983B15D24EF2",
                    "download": "BAD03DD48A4834D0C4D2E0C57EE113A1"
                },
                "uat_featuretest5": {
                    "gid": "B3FDF06B4E3CC14673A9BCBFE1646903",
                    "size": "38865C90A560DF4CF24B81829529F682",
                    "download": "6B4F33DE48702D8EDBCF70EE519BA4D2"
                },
                "uat_featuretest6": {
                    "gid": "260037891605FF7D965BB619A4C49E40",
                    "size": "F25652482D7A5D65DFD03FA823F9BF51",
                    "download": "A4AFC29AAB17840C7FF7356FF3E37D3C"
                },
                "uat_featuretest7": {
                    "gid": "ACCE4D0A8AA0B122BB5CCDA1A9C71BD4",
                    "size": "DC0DB576EE64DF0F5271341B18EF5191",
                    "download": "FDEBB9A827CA5C47861A06A9CF324ED8"
                },
                "uat_featuretest8": {
                    "gid": "7D056B8E10F8E37EC7354A10A8B3B7E4",
                    "size": "B942AE8B97D69D177FB29A660EA07A2C",
                    "download": "0CD4B0F742E0BD4639332BBDCF02EB41"
                },
                "uat_featuretest9": {
                    "gid": "554A14E2E34FE282B4CBC72CF4E0EBCD",
                    "size": "051F911A13D52E0C00603B0223584718",
                    "download": "9AB3729CC4F85DE05A47B03E546C8C69"
                },
                "uat_functionality_test": {
                    "gid": "03AAA07FA5ABA7CCDFE4421D37936509",
                    "size": "BBFCDCE47175528CF34CD40CACA4EB04",
                    "download": "BE548C141DF2EE1B9D3F27B9363C6CDD"
                },
                "uat_main": {
                    "gid": "99471DECBF5E4449CB46215C0F76D0E2",
                    "size": "F2A117E817B3B42F4984DF0FBD9BAA59",
                    "download": "C75DE17A9D9968392B088EFCBBF61664"
                },
                "uat_main_rc": {
                    "gid": "ED1DA64EB75139ECDD33B7F1D844D7FD",
                    "size": "62015A39B5F4873F329E30688030702D",
                    "download": "8B8EF0EFFEB718165CADF10204D1DBE0"
                },
                "uat_ppt": {
                    "gid": "86B85768801A49655FC3148DF528FACD",
                    "size": "1A759F9B1397345B1A7855FABDD97EE7",
                    "download": "7D59594D1E1ECE67FCD2877ED980F41E"
                },
                "uat_release": {
                    "gid": "A64D8A600080B9F59380FE31644EB6A6",
                    "size": "0107EF8B49864D7BA3158DBD5CCA9339",
                    "download": "274ADA67E23DA19A6035BC10D8B27CA9"
                },
                "uat_tct": {
                    "gid": "C96DDADC350A7ECC18306101F1EB0608",
                    "size": "1BB319A31B0DA5F759847238C16C6D47",
                    "download": "FD1C1036F36E7A510D55877038B5A77F"
                }
            }
        },
        "774963": {
            "config": {
                "oslist": "linux",
                "osarch": "64",
                "language": ""
            },
            "manifests": {
                "public": {
                    "gid": "919858418026913339",
                    "size": "10945406481",
                    "download": "3370302224"
                }
            },
            "encryptedmanifests": {
                "uat_community_hosting": {
                    "gid": "A13E2988BF3DB3EB26E2072C179701FE",
                    "size": "C689B445FD6E6526D26DCD33015CCBE0",
                    "download": "5B8BDD613327D58636F2ACEBCAC8E1BE"
                },
                "uat_content": {
                    "gid": "D8B26595B7F4AF187A13C328A227C656",
                    "size": "FDE7ACC67DB25DBF77EF3E5E6032F9CD",
                    "download": "3D8AF55B922F895EFB79340621E585B3"
                },
                "uat_content_pt": {
                    "gid": "11EA3C21F750F9314C620E65821B03EE",
                    "size": "135281B915B2DA6EA53D75AD2F9D443F",
                    "download": "C43BD270563C9B7520EBAC566A748B16"
                },
                "uat_cpt": {
                    "gid": "67C077BF4CCBE639486C9706CA283BAF",
                    "size": "5A07ECB0C3979E4272F185BC6D89EC21",
                    "download": "9802AC786DCFBACE2AB2E662B2BDA0B0"
                },
                "uat_crashtest": {
                    "gid": "DA98B509B17706FBC7FA3636807BD805",
                    "size": "24A0E71E0BD9BAC74016EC317DC1B914",
                    "download": "513CE2A35F99C3645F2CCE9E1698781D"
                },
                "uat_features": {
                    "gid": "1BB1BFD233054AB15200840763B80D02",
                    "size": "2F532EF6A49766DCD19CAB5236FC2FA4",
                    "download": "CCDE0018A4779C235D76B78F572F02B0"
                },
                "uat_features_rc": {
                    "gid": "1E13CCD6C73A4656BF6F3347BBB8C4A5",
                    "size": "8FAFF44508BF5257DB9D7F7A14F7AB8D",
                    "download": "86C82BC7836FF88C5738B33CD354C4C1"
                },
                "uat_featuretest1": {
                    "gid": "30E3B18BF68E756E26289C617340E646",
                    "size": "5711F1887F2CAE8D8131BEEE5D90891E",
                    "download": "E910F3C321208CC6093A07F62590E4ED"
                },
                "uat_featuretest10": {
                    "gid": "6D8409970BC4D5D9F8CCFF85E4CCACDB",
                    "size": "5FB24C00551BA95600AE652D1D296EF6",
                    "download": "5858F7A2196BD4B4C884EA984F247AA5"
                },
                "uat_featuretest11": {
                    "gid": "83B2695CE6912512E3BB914C039CDD84",
                    "size": "FE9DAE3D3B88821F85631811140FEE56",
                    "download": "590E23D4C857039CFBFA2DB4418B8486"
                },
                "uat_featuretest2": {
                    "gid": "0F28B7B8EC535A0245A700F9C6604E56",
                    "size": "BF01356BB34EB7A9D83DD527639DD1EE",
                    "download": "72B0BE5B8B6C459C5644B586D0D38000"
                },
                "uat_featuretest3": {
                    "gid": "2350688774D92B0384D3D577EA4E610A",
                    "size": "D297F543405AA15B4B1918ECBE843835",
                    "download": "5C81289248FCE9FB27ADDF563EB0A43B"
                },
                "uat_featuretest4": {
                    "gid": "695C252C2C8FB6FD409AFB014176EE5E",
                    "size": "5719DFA536F5F71E9D67EC7BA01E129F",
                    "download": "7E8A2441471B80B49BD7DF8AFFA4DA09"
                },
                "uat_featuretest5": {
                    "gid": "6A6284484A8D57E97F5B955B385401A8",
                    "size": "D6E0725DEB11C66AC951C622DAD75DC6",
                    "download": "6874D2267E01AD0C1956EC2D83AEFFF4"
                },
                "uat_featuretest6": {
                    "gid": "1DA571AB16E16E0390D232E2D327B58D",
                    "size": "5EBBCEDEF9A64BCBCFCD455A0CC21843",
                    "download": "9C3EF4C744CFD31212C50F2D953D86C9"
                },
                "uat_featuretest7": {
                    "gid": "03537CBFF443390DC749D54FDC337E61",
                    "size": "D1917949C6D424469E254C062BC2C470",
                    "download": "8E5FB4EBE1236874E31AC30337F77FC3"
                },
                "uat_featuretest8": {
                    "gid": "9D335FA35F32BE4D6E57054FBC4C0927",
                    "size": "1E03CB79B5FC05AC3D12DC92CE7C6A01",
                    "download": "08222BBFDBBA351B5B4D5426DD20042E"
                },
                "uat_featuretest9": {
                    "gid": "235C1A1C776FF6212D7A7370C5DBD14F",
                    "size": "37A53BD2D930494E421BA576EB7DA74B",
                    "download": "7DFF8B352E5AF36AEAFE9202B27D2849"
                },
                "uat_functionality_test": {
                    "gid": "DBE15478712BD47EFEB37748804B4A9E",
                    "size": "B3A1A8FFD7363FBD5B892A01769B6F7F",
                    "download": "3EBFDDE3173A17739073366EE4DB77AE"
                },
                "uat_main": {
                    "gid": "0F30796F4A598B790EC8F7B991FD6DB5",
                    "size": "7FDC6E017EB5F100B0F2ECB9DFD3B1FA",
                    "download": "460CD3E96D8C0AFEA8506C49292B5003"
                },
                "uat_main_rc": {
                    "gid": "26B424A1128915CC365249289667D3FF",
                    "size": "473B8E9A6320B8F66F16134503C80155",
                    "download": "1BA4A6D8003161DD04193361963A38AC"
                },
                "uat_ppt": {
                    "gid": "39DFFC7555F2CD66E270A0EDC2124A9E",
                    "size": "852DBD87B3BE209DA2BAC83DD1CB2B6C",
                    "download": "CB64CB146BD39CE37F76E6255705317C"
                },
                "uat_release": {
                    "gid": "8134E22195963E5B22C04C5F55B86B88",
                    "size": "C0D7E019AD7F8696A65ACD092B5E494E",
                    "download": "630B19B92E8FAD6C16E30F8578CAB64E"
                },
                "uat_tct": {
                    "gid": "B1B9BFC105B0CD27D5509F4316DF163A",
                    "size": "6D13EBB8FE293BE376BD6222B164472B",
                    "download": "D71EB936D92CE2698E3F27C43C507BF3"
                }
            }
        },
        "774943": {
            "config": {
                "language": ""
            },
            "manifests": {
                "public": {
                    "gid": "2545188719619349744",
                    "size": "0",
                    "download": "0"
                }
            },
            "encryptedmanifests": {
                "hlod_test": {
                    "gid": "C61F80B4E4AFEB741542B6098D5696DD",
                    "size": "4095C34B589140809F564C4E3814F21B",
                    "download": "4095C34B589140809F564C4E3814F21B"
                },
                "uat_content": {
                    "gid": "0505302424EBCA4D12101E235BDEB350",
                    "size": "6F4FA7C9A6A84F34C63A61904944DA2A",
                    "download": "6F4FA7C9A6A84F34C63A61904944DA2A"
                },
                "uat_content_pt": {
                    "gid": "F632DE1598253ABECF3FD0DC3A77C780",
                    "size": "68D81F38EEC3E90AE9D95BDD3D6BE028",
                    "download": "68D81F38EEC3E90AE9D95BDD3D6BE028"
                },
                "uat_cpt": {
                    "gid": "FA2CE6C96325E0DA129E637D4A80FE59",
                    "size": "C5A23EFF99C31936C6A26D2A36153C15",
                    "download": "C5A23EFF99C31936C6A26D2A36153C15"
                },
                "uat_crashtest": {
                    "gid": "677F729708882195B049814A86DF56E2",
                    "size": "BD94C881D1B3AFF558BBDF4732FDFC9C",
                    "download": "BD94C881D1B3AFF558BBDF4732FDFC9C"
                },
                "uat_experimental": {
                    "gid": "7073AC6A1F5D3F8FD0099CABE7101F70",
                    "size": "C5DEB4226880005568890D715AFA74CB",
                    "download": "C5DEB4226880005568890D715AFA74CB"
                },
                "uat_features": {
                    "gid": "2AEB2FCF4ACE50C7610FE16FAE4883FF",
                    "size": "1455FB16EE1AB6CC7FC36EED79E69F29",
                    "download": "7DB2E48EF93FDD6660779EB687411E55"
                },
                "uat_featuretest1": {
                    "gid": "340EEE3C16B67362A33EF5928AA429FB",
                    "size": "41DCC291562C449C49044BF206DF2286",
                    "download": "41DCC291562C449C49044BF206DF2286"
                },
                "uat_featuretest10": {
                    "gid": "EB801BE8CE87CFDD0B1CC998188AC112",
                    "size": "37868179A18A463D77CECE610C6CC7ED",
                    "download": "37868179A18A463D77CECE610C6CC7ED"
                },
                "uat_featuretest11": {
                    "gid": "9E783C8430CB7ACE52E3A89919802314",
                    "size": "B48750793E81C617B21D858D86E064E7",
                    "download": "B48750793E81C617B21D858D86E064E7"
                },
                "uat_featuretest2": {
                    "gid": "86972021487FD6E6DC35FDDE97AEE3F2",
                    "size": "B417A61A34B3FF1545116CF7F5A80AF1",
                    "download": "B417A61A34B3FF1545116CF7F5A80AF1"
                },
                "uat_featuretest3": {
                    "gid": "4FBAB2AAB78A6F5B695BE6AA7BD8501D",
                    "size": "F75CC073713EC63696DC4BACB7BF28A2",
                    "download": "F75CC073713EC63696DC4BACB7BF28A2"
                },
                "uat_featuretest4": {
                    "gid": "F6E66161283B3DDBC468BEB0831B4F2B",
                    "size": "BC6696054FC38DBC713907297C02AC57",
                    "download": "BC6696054FC38DBC713907297C02AC57"
                },
                "uat_featuretest5": {
                    "gid": "B13D9F13279F5D3B182BC0B637FC8FAE",
                    "size": "73876BAF9874667AA8C5363204DED388",
                    "download": "73876BAF9874667AA8C5363204DED388"
                },
                "uat_featuretest6": {
                    "gid": "1272678EBA06394D35BA747B711CCC1C",
                    "size": "123697C0C29D1787C7F9C33E32CBEFFA",
                    "download": "123697C0C29D1787C7F9C33E32CBEFFA"
                },
                "uat_featuretest7": {
                    "gid": "00172ACFC4FFBF3AEA4A436461AA2EFA",
                    "size": "55A55D04A9AEB83296CDDCA8167A81CE",
                    "download": "55A55D04A9AEB83296CDDCA8167A81CE"
                },
                "uat_featuretest8": {
                    "gid": "387F5F94080D27CD2D336B30EB7FB0DD",
                    "size": "9808CC299D7814CD1F868CBCE664E86B",
                    "download": "9808CC299D7814CD1F868CBCE664E86B"
                },
                "uat_featuretest9": {
                    "gid": "2E05323A150F5DFDB4897312AACF96B5",
                    "size": "337D2B09F677377F4BC2BF13B71AFA2E",
                    "download": "337D2B09F677377F4BC2BF13B71AFA2E"
                },
                "uat_functionality_test": {
                    "gid": "B7168BC0E92D232CC4A7ADA31609337F",
                    "size": "D0F01D97185EA8F1C93E08542B8F34E0",
                    "download": "D0F01D97185EA8F1C93E08542B8F34E0"
                },
                "uat_internalpt": {
                    "gid": "545C1C4C1FCCA0CC3917A5C38B49E6D3",
                    "size": "0307E9AEADA5F00A6CB1A2EA045D63B3",
                    "download": "0307E9AEADA5F00A6CB1A2EA045D63B3"
                },
                "uat_main": {
                    "gid": "A346F26486CF0A9F88D880F78D7A7146",
                    "size": "C4D69AAE99AA91F1D96542939FC96B1E",
                    "download": "C4D69AAE99AA91F1D96542939FC96B1E"
                },
                "uat_ppt": {
                    "gid": "557EA36B35B1948855C3E80574ED22B5",
                    "size": "B63D43CDE05E5E0541C646ACBFACC18B",
                    "download": "B63D43CDE05E5E0541C646ACBFACC18B"
                },
                "uat_release": {
                    "gid": "24D6B51B7372267311E1CD8CC3286466",
                    "size": "835D2A2253CD9A16AECC04A520F61A31",
                    "download": "835D2A2253CD9A16AECC04A520F61A31"
                }
            },
            "depotfromapp": "774941"
        },
        "branches": {
            "public": {
                "buildid": "7494375",
                "timeupdated": "1633693857"
            },
            "uat_community_hosting": {
                "buildid": "10107162",
                "pwdrequired": "1",
                "timeupdated": "1670525463"
            },
            "uat_content": {
                "buildid": "11402823",
                "pwdrequired": "1",
                "timeupdated": "1686041349"
            },
            "uat_content_pt": {
                "buildid": "11249745",
                "pwdrequired": "1",
                "timeupdated": "1684293846"
            },
            "uat_cpt": {
                "buildid": "11340322",
                "pwdrequired": "1",
                "timeupdated": "1685396888"
            },
            "uat_crashtest": {
                "buildid": "11239735",
                "pwdrequired": "1",
                "timeupdated": "1684254713"
            },
            "uat_features": {
                "buildid": "6075329",
                "pwdrequired": "1",
                "timeupdated": "1611010726"
            },
            "uat_features_rc": {
                "buildid": "5206646",
                "pwdrequired": "1",
                "timeupdated": "1592965032"
            },
            "uat_featuretest1": {
                "buildid": "11346596",
                "pwdrequired": "1",
                "timeupdated": "1685569895"
            },
            "uat_featuretest10": {
                "buildid": "11400837",
                "pwdrequired": "1",
                "timeupdated": "1686015657"
            },
            "uat_featuretest11": {
                "buildid": "10991026",
                "pwdrequired": "1",
                "timeupdated": "1681354374"
            },
            "uat_featuretest2": {
                "buildid": "11397017",
                "pwdrequired": "1",
                "timeupdated": "1685978375"
            },
            "uat_featuretest3": {
                "buildid": "11310515",
                "pwdrequired": "1",
                "timeupdated": "1685040923"
            },
            "uat_featuretest4": {
                "buildid": "11329762",
                "pwdrequired": "1",
                "timeupdated": "1686071971"
            },
            "uat_featuretest5": {
                "buildid": "11405411",
                "pwdrequired": "1",
                "timeupdated": "1686062422"
            },
            "uat_featuretest6": {
                "buildid": "11402190",
                "pwdrequired": "1",
                "timeupdated": "1686034390"
            },
            "uat_featuretest7": {
                "buildid": "11371178",
                "pwdrequired": "1",
                "timeupdated": "1685631545"
            },
            "uat_featuretest8": {
                "buildid": "11365586",
                "pwdrequired": "1",
                "timeupdated": "1685986571"
            },
            "uat_featuretest9": {
                "buildid": "11221957",
                "pwdrequired": "1",
                "timeupdated": "1683928955"
            },
            "uat_functionality_test": {
                "buildid": "10840843",
                "pwdrequired": "1",
                "timeupdated": "1679593610"
            },
            "uat_main": {
                "buildid": "10725140",
                "pwdrequired": "1",
                "timeupdated": "1678383058"
            },
            "uat_main_rc": {
                "buildid": "5862657",
                "pwdrequired": "1",
                "timeupdated": "1606165095"
            },
            "uat_ppt": {
                "buildid": "10725140",
                "pwdrequired": "1",
                "timeupdated": "1678410775"
            },
            "uat_release": {
                "buildid": "11409290",
                "pwdrequired": "1",
                "timeupdated": "1686096246"
            },
            "uat_tct": {
                "buildid": "9972864",
                "pwdrequired": "1",
                "timeupdated": "1668834106"
            },
            "hlod_test": {
                "buildid": "8410387",
                "pwdrequired": "1",
                "timeupdated": "1647875304"
            },
            "uat_experimental": {
                "buildid": "9855771",
                "pwdrequired": "1",
                "timeupdated": "1667859150"
            },
            "uat_internalpt": {
                "buildid": "10017370",
                "pwdrequired": "1",
                "timeupdated": "1669391140"
            }
        }
    },
    "_missing_token": false,
    "_change_number": 19073526,
    "_sha": "cdb52717c5ce5945c0091f4c0e7981aeb897529d",
    "_size": 18580
}