{
    "appid": "944490",
    "common": {
        "name": "Vox Machinae Dedicated Server",
        "type": "Tool",
        "parent": "334540",
        "oslist": "windows,linux",
        "osarch": "64",
        "logo": "8459e33710e4ae2b4801466c13b56e6bd177e40d",
        "logo_small": "8459e33710e4ae2b4801466c13b56e6bd177e40d_thumb",
        "icon": "b715532aeeffa793b7862cc4036ddce9c5b4c5ef",
        "clienticon": "332ac820c356157f64ae4b8bcf07d8e495751467",
        "clienttga": "68ba94b00d1ecab68a3a63ede5183a1321a0e27f",
        "releasestate": "released",
        "associations": {},
        "gameid": "944490"
    },
    "config": {
        "installdir": "Vox Machinae Dedicated Server",
        "launch": {
            "0": {
                "executable": "vmserver.exe",
                "arguments": "-bots -playlist \"playlist.txt\"",
                "type": "default",
                "config": {
                    "oslist": "windows",
                    "osarch": "64"
                }
            },
            "1": {
                "executable": "vmserver.x86_64",
                "arguments": "-bots -playlist \"playlist.txt\"",
                "type": "default",
                "config": {
                    "oslist": "linux",
                    "osarch": "64"
                }
            }
        }
    },
    "depots": {
        "1004": {
            "name": "Steamworks SDK Redist (WIN32)",
            "config": {
                "oslist": "windows"
            },
            "manifests": {
                "public": "5329354416203291021"
            },
            "maxsize": "42086632",
            "depotfromapp": "1007"
        },
        "1005": {
            "name": "Steamworks SDK Redist (OSX32)",
            "config": {
                "oslist": "macos"
            },
            "manifests": {
                "public": "2135359612286175146"
            },
            "depotfromapp": "1007"
        },
        "1006": {
            "name": "Steamworks SDK Redist (LINUX32)",
            "config": {
                "oslist": "linux"
            },
            "manifests": {
                "public": "4444585935428744334"
            },
            "maxsize": "66706004",
            "depotfromapp": "1007"
        },
        "944491": {
            "name": "Vox Machinae Dedicated Server Content",
            "manifests": {
                "public": "6215797843193933326",
                "stable": "3309836361661249831"
            },
            "maxsize": "47721348"
        },
        "944492": {
            "name": "Vox Machinae Dedicated Server Linux",
            "config": {
                "oslist": "linux"
            },
            "manifests": {
                "public": "7536476504296219009",
                "stable": "495428223912398638"
            },
            "maxsize": "106744263"
        },
        "944494": {
            "name": "Vox Machinae Dedicated Server Windows",
            "config": {
                "oslist": "windows"
            },
            "manifests": {
                "public": "2082688812560147986",
                "stable": "8101331890116151240"
            },
            "maxsize": "77787423"
        },
        "branches": {
            "public": {
                "buildid": "9040217",
                "timeupdated": "1656631300"
            },
            "beta": {
                "buildid": "9040217",
                "description": "pre-release testing",
                "timeupdated": "1656631317"
            },
            "stable": {
                "buildid": "6368284",
                "description": "stable branch for commercial users",
                "timeupdated": "1646418142"
            }
        }
    },
    "_missing_token": false,
    "_change_number": 15289102,
    "_sha": "5f0a73494cd32071c88fad6cf8e525ac2b2acfcc",
    "_size": 2670
}